amazon_braket_simulator_v2-0.3.4.dist-info/licenses/LICENSE
amazon_braket_simulator_v2-0.3.4.dist-info/licenses/NOTICE
braket/juliapkg.json
braket/simulator_v2/__init__.py
braket/simulator_v2/_version.py
braket/simulator_v2/base_simulator_v2.py
braket/simulator_v2/density_matrix_simulator_v2.py
braket/simulator_v2/julia_workers.py
braket/simulator_v2/state_vector_simulator_v2.py
amazon_braket_simulator_v2-0.3.4.dist-info/METADATA
amazon_braket_simulator_v2-0.3.4.dist-info/WHEEL
amazon_braket_simulator_v2-0.3.4.dist-info/entry_points.txt
amazon_braket_simulator_v2-0.3.4.dist-info/top_level.txt
amazon_braket_simulator_v2-0.3.4.dist-info/RECORD
