Metadata-Version: 2.4
Name: amazon-braket-simulator-v2
Version: 0.3.4
Summary: Local simulation of quantum circuits
License: 
Classifier: Development Status :: 4 - Beta
Classifier: Intended Audience :: Developers
Classifier: Natural Language :: English
Classifier: License :: OSI Approved :: Apache Software License
Classifier: Programming Language :: Python
Classifier: Programming Language :: Python :: 3.10
Classifier: Programming Language :: Python :: 3.11
Classifier: Programming Language :: Python :: 3.12
Classifier: Programming Language :: Python :: 3.13
Classifier: Operating System :: OS Independent
Requires-Python: >=3.10
License-File: LICENSE
License-File: NOTICE
Requires-Dist: juliacall==0.9.23
Requires-Dist: numpy
Requires-Dist: amazon-braket-schemas>=1.20.2
Requires-Dist: amazon-braket-sdk>=1.83.0
Provides-Extra: test
Requires-Dist: amazon-braket-pennylane-plugin; extra == "test"
Requires-Dist: pre-commit; extra == "test"
Requires-Dist: pylint; extra == "test"
Requires-Dist: pytest; extra == "test"
Requires-Dist: pytest-benchmark; extra == "test"
Requires-Dist: pytest-cov; extra == "test"
Requires-Dist: pytest-rerunfailures; extra == "test"
Requires-Dist: pytest-timeout; extra == "test"
Requires-Dist: pytest-xdist; extra == "test"
Requires-Dist: qiskit==1.4.3; extra == "test"
Requires-Dist: qiskit-braket-provider==0.6.0; extra == "test"
Requires-Dist: qiskit-algorithms==0.3.1; extra == "test"
Requires-Dist: ruff; extra == "test"
Requires-Dist: sphinx; extra == "test"
Requires-Dist: sphinx-rtd-theme; extra == "test"
Requires-Dist: sphinxcontrib-apidoc; extra == "test"
Requires-Dist: tox; extra == "test"
Dynamic: license-file
